MANIFEST.in
README.rst
setup.py
aliyunsdkrds/__init__.py
aliyunsdkrds/request/__init__.py
aliyunsdkrds/request/v20140815/AddTagsToResourceRequest.py
aliyunsdkrds/request/v20140815/AllocateInstancePrivateConnectionRequest.py
aliyunsdkrds/request/v20140815/AllocateInstancePublicConnectionRequest.py
aliyunsdkrds/request/v20140815/AllocateReadWriteSplittingConnectionRequest.py
aliyunsdkrds/request/v20140815/CalculateDBInstanceWeightRequest.py
aliyunsdkrds/request/v20140815/CancelImportRequest.py
aliyunsdkrds/request/v20140815/CheckAccountNameAvailableRequest.py
aliyunsdkrds/request/v20140815/CheckDBNameAvailableRequest.py
aliyunsdkrds/request/v20140815/CheckRecoveryConditionsRequest.py
aliyunsdkrds/request/v20140815/CheckResourceRequest.py
aliyunsdkrds/request/v20140815/CloneDBInstanceRequest.py
aliyunsdkrds/request/v20140815/CopyDatabaseRequest.py
aliyunsdkrds/request/v20140815/CreateAccountRequest.py
aliyunsdkrds/request/v20140815/CreateBackupRequest.py
aliyunsdkrds/request/v20140815/CreateDBInstanceReplicaRequest.py
aliyunsdkrds/request/v20140815/CreateDBInstanceRequest.py
aliyunsdkrds/request/v20140815/CreateDampPolicyRequest.py
aliyunsdkrds/request/v20140815/CreateDatabaseRequest.py
aliyunsdkrds/request/v20140815/CreateDiagnosticReportRequest.py
aliyunsdkrds/request/v20140815/CreateMigrateTaskForSQLServerRequest.py
aliyunsdkrds/request/v20140815/CreateMigrateTaskRequest.py
aliyunsdkrds/request/v20140815/CreateOnlineDatabaseTaskRequest.py
aliyunsdkrds/request/v20140815/CreatePolicyWithSpecifiedPolicyRequest.py
aliyunsdkrds/request/v20140815/CreateReadOnlyDBInstanceRequest.py
aliyunsdkrds/request/v20140815/CreateSQLDiagnosisRequest.py
aliyunsdkrds/request/v20140815/CreateStaticVerificationRequest.py
aliyunsdkrds/request/v20140815/CreateTempDBInstanceRequest.py
aliyunsdkrds/request/v20140815/DegradeDBInstanceSpecRequest.py
aliyunsdkrds/request/v20140815/DeleteAccountRequest.py
aliyunsdkrds/request/v20140815/DeleteBackupRequest.py
dd_aliyun_python_sdk_rds.egg-info/PKG-INFO
dd_aliyun_python_sdk_rds.egg-info/SOURCES.txt
dd_aliyun_python_sdk_rds.egg-info/dependency_links.txt
dd_aliyun_python_sdk_rds.egg-info/requires.txt
dd_aliyun_python_sdk_rds.egg-info/top_level.txt